CHANGELOG.md
DCO
pytest_helm_charts/__init__.py
pytest_helm_charts/apps/__init__.py
pytest_helm_charts/apps/app_catalog.py
pytest_helm_charts/apps/deployment.py
pytest_helm_charts/apps/http_testing.py
pytest_helm_charts/clusters.py
pytest_helm_chart-0.1.1.dist-info/entry_points.txt
pytest_helm_chart-0.1.1.dist-info/LICENSE
pytest_helm_chart-0.1.1.dist-info/WHEEL
pytest_helm_chart-0.1.1.dist-info/METADATA
pytest_helm_chart-0.1.1.dist-info/RECORD
