Metadata-Version: 2.1
Name: pytest-helm-chart
Version: 0.1.1
Summary: A plugin to provide different types and configs of Kubernetes clusters that can be used for testing.
Home-page: https://github.com/giantswarm/pytest-helm-chart
License: Apache-2.0
Keywords: kubernetes,helm,chart
Author: Łukasz Piątkowski
Author-email: lukasz@giantswarm.io
Requires-Python: >=3.6,<4.0
Classifier: Development Status :: 4 - Beta
Classifier: Framework :: Pytest
Classifier: Intended Audience :: Developers
Classifier: License :: OSI Approved :: Apache Software License
Classifier: Operating System :: OS Independent
Classifier: Programming Language :: Python
Classifier: Programming Language :: Python :: 3
Classifier: Programming Language :: Python :: 3.6
Classifier: Programming Language :: Python :: 3.7
Classifier: Programming Language :: Python :: 3.8
Classifier: Programming Language :: Python :: Implementation :: CPython
Classifier: Topic :: Software Development :: Testing
Requires-Dist: pykube-ng (>=20.5.0,<21.0.0)
Requires-Dist: pytest (>=5.4.2,<6.0.0)
Project-URL: Repository, https://github.com/giantswarm/pytest-helm-chart
